COPYRIGHT
MANIFEST.in
Makefile
README
setup.py
test/__init__.py
test/__init__.pyc
test/test_compile.py
test/test_compile.pyc
test/test_cookie_domain.py
test/test_cookie_domain.pyc
tiddlywebplugins/__init__.py
tiddlywebplugins/cookiedomain.py
tiddlywebplugins.cookiedomain.egg-info/PKG-INFO
tiddlywebplugins.cookiedomain.egg-info/SOURCES.txt
tiddlywebplugins.cookiedomain.egg-info/dependency_links.txt
tiddlywebplugins.cookiedomain.egg-info/namespace_packages.txt
tiddlywebplugins.cookiedomain.egg-info/not-zip-safe
tiddlywebplugins.cookiedomain.egg-info/requires.txt
tiddlywebplugins.cookiedomain.egg-info/top_level.txt