Metadata-Version: 1.0
Name: tiddlywebplugins.cookiedomain
Version: 0.8
Summary: TiddlyWeb plugin adjust the domain of a cookie
Home-page: http://pypi.python.org/pypi/tiddlywebplugins.cookiedomain
Author: Chris Dent
Author-email: cdent@peermore.com
License: BSD
Platform: Posix; MacOS X; Windows
